{
  "name": "iconfont-sprite",
  "hash": "sha256-3f571e959d46088f088312ea5f0ca9603aae9ffbff76af44a9b1bdbf4813bef8",
  "sources": ["src/assets/iconfont/vendor/iconfont.js"],
  "output": "src/assets/iconfont/generated/IconfontSprite.tsx",
  "symbolCount": 87,
  "symbols": [
    "icon-yinhang-shanghaipudongfazhan-",
    "icon-yinhang-zhongguorenminyinhang-",
    "icon-huifengyinhang",
    "icon-yinhang-zhongguoyinhang",
    "icon-jiaotongyinhang",
    "icon-shenqingchenggong",
    "icon-yishenhe",
    "icon-daishenhe",
    "icon-tongguo",
    "icon-yiguidang",
    "icon-chehui",
    "icon-shenpitongguo_1",
    "icon-yijujue",
    "icon-xingye",
    "icon-iconfonttuijianren",
    "icon-daoqishijian",
    "icon-ding",
    "icon-shenfenzheng",
    "icon-shoujihao",
    "icon-qianyue",
    "icon-shenpi",
    "icon-yaoqingma",
    "icon-fujian",
    "icon-qianqigoutong",
    "icon-xiaoxi",
    "icon-caifang-danweilianxirendianhua",
    "icon-remove-role",
    "icon-add-role",
    "icon-setting-role",
    "icon-edit-role",
    "icon-beizhu",
    "icon-dianfeidan",
    "icon-xiugaimima",
    "icon-authority",
    "icon-gongsidizhi",
    "icon-shenpi1",
    "icon-shenpijiedian",
    "icon-yinhangmingcheng",
    "icon-IDxingmingzhengjian",
    "icon-B-shengshiqu",
    "icon-yinhangqiahao",
    "icon-yewufencheng",
    "icon-mima",
    "icon-expanded",
    "icon-shiyongwendang",
    "icon-success_icon",
    "icon-saomiaojian",
    "icon-shengshiqu",
    "icon-menu_collasped",
    "icon-dashboard",
    "icon-fengzhi",
    "icon-guzhi",
    "icon-Body_shangchuansaomiaojian",
    "icon-jianfengpinggu",
    "icon-gongzitongji",
    "icon-nianyongdianliang",
    "icon-ziyuan203",
    "icon-zhiwuquanxian",
    "icon-lianxiren",
    "icon-Switchtothepricemode",
    "icon-status",
    "icon-49",
    "icon-003-price-tag",
    "icon-gudingjiacha",
    "icon-daoqishijian1",
    "icon--jiageleixing-gai",
    "icon-xinxibuquan",
    "icon-henggang",
    "icon-dailishang",
    "icon-nianyongdianliang1",
    "icon-butongguo",
    "icon-qianyueliebiao",
    "icon-shenpiliucheng",
    "icon-a-yonghuliebiao3x",
    "icon-menu_collasped1",
    "icon-gudingjiage",
    "icon-ABC",
    "icon-China_Citic_Back",
    "icon-China_Post",
    "icon-China_Merchants_Bank",
    "icon-ICBC",
    "icon-China_Guangfa_Bank",
    "icon-jiansheyinhang",
    "icon-captcha",
    "icon-phone-captcha",
    "icon-github",
    "icon-wechat"
  ],
  "generatedAt": "2026-04-27T16:16:55.271Z"
}
